mstr/__init__.py
mstr/requests/__init__.py
mstr/requests/rest/__init__.py
mstr/requests/rest/authenticated_session.py
mstr/requests/rest/base.py
mstr/requests/rest/errors.py
mstr/requests/rest/exceptions.py
mstr/requests/rest/mixins.py
mstr/requests/rest/session.py
mstr/requests/rest/api/__init__.py
mstr/requests/rest/api/auth.py
mstr/requests/rest/api/projects.py
mstr/requests/rest/api/sessions.py
mstr/requests/rest/api/utils.py
mstr_rest_requests-0.15.0.dist-info/METADATA
mstr_rest_requests-0.15.0.dist-info/WHEEL
mstr_rest_requests-0.15.0.dist-info/licenses/LICENSE
mstr_rest_requests-0.15.0.dist-info/RECORD
