Metadata-Version: 2.4
Name: mstr-rest-requests
Version: 0.15.0
Summary: Easily make requests of the MicroStrategy REST API
Project-URL: Repository, https://github.com/paulbailey/mstr-rest-requests
Author-email: Paul Bailey <bailey@dreamshake.net>
License-Expression: Apache-2.0
License-File: LICENSE
Requires-Python: <4,>=3.9
Requires-Dist: requests
Requires-Dist: requests-toolbelt
